visier_api_data_out/__init__.py
visier_api_data_out/py.typed
visier_api_data_out/api/__init__.py
visier_api_data_out/api/data_query_api.py
visier_api_data_out/api/data_version_export_api.py
visier_api_data_out/api/reporting_api.py
visier_api_data_out/api/search_api.py
visier_api_data_out/api/source_files_download_api.py
visier_api_data_out/api/vee_api.py
visier_api_data_out/models/__init__.py
visier_api_data_out/models/analysis_common_report_create_request_dto.py
visier_api_data_out/models/analysis_common_report_delete_success_dto.py
visier_api_data_out/models/analysis_common_report_dto.py
visier_api_data_out/models/analysis_common_report_list_response_dto.py
visier_api_data_out/models/analysis_common_vee_clarification_dto.py
visier_api_data_out/models/analysis_common_vee_conversation_dto.py
visier_api_data_out/models/analysis_common_vee_conversation_state_dto.py
visier_api_data_out/models/analysis_common_vee_corrections_dto.py
visier_api_data_out/models/analysis_common_vee_data_dto.py
visier_api_data_out/models/analysis_common_vee_feedback_dto.py
visier_api_data_out/models/analysis_common_vee_options_dto.py
visier_api_data_out/models/analysis_common_vee_question_dto.py
visier_api_data_out/models/analysis_common_vee_response_dto.py
visier_api_data_out/models/analysis_common_vee_response_schema_dto.py
visier_api_data_out/models/analysis_common_vee_response_schema_reference_dto.py
visier_api_data_out/models/analysis_common_vee_sample_question_dto.py
visier_api_data_out/models/analysis_common_vee_sample_question_library_dto.py
visier_api_data_out/models/analysis_common_vee_status_code_dto.py
visier_api_data_out/models/analysis_common_vee_visual_dto.py
visier_api_data_out/models/analysis_common_vee_visual_options_dto.py
visier_api_data_out/models/data_out_list_response.py
visier_api_data_out/models/dataservices_common_dimension_member_reference_dto.py
visier_api_data_out/models/dataservices_common_member_values_dto.py
visier_api_data_out-22222222.99201.1906.dist-info/METADATA
visier_api_data_out-22222222.99201.1906.dist-info/WHEEL
visier_api_data_out-22222222.99201.1906.dist-info/top_level.txt
visier_api_data_out-22222222.99201.1906.dist-info/RECORD
